Mensajes/__init__.py
Mensajes/adios/__init__.py
Mensajes/adios/despedidas.py
Mensajes/hola/__init__.py
Mensajes/hola/saludos.py
tests/__init__.py
tests/test_hola.py
Mensajes_Vyka-5.0.dist-info/LICENSE
Mensajes_Vyka-5.0.dist-info/METADATA
Mensajes_Vyka-5.0.dist-info/WHEEL
Mensajes_Vyka-5.0.dist-info/top_level.txt
Mensajes_Vyka-5.0.dist-info/RECORD
