Metadata-Version: 2.1
Name: Mensajes-Vyka
Version: 5.0
Summary: Un paquete para saludar y despedir
Home-page: https://www.davidrojas.com
Author: David Rojas
Author-email: rojasdavid9618@gmail.com
Classifier: Development Status :: 1 - Planning
Classifier: Environment :: Console
Classifier: Intended Audience :: Education
Classifier: License :: OSI Approved :: MIT License
Classifier: Natural Language :: Spanish
Classifier: Operating System :: OS Independent
Classifier: Programming Language :: Python :: 3.11
Classifier: Topic :: Utilities
License-File: LICENSE
Requires-Dist: numpy (>=1.23.0)
